inventory_foundation_sdk/__init__.py
inventory_foundation_sdk/_modidx.py
inventory_foundation_sdk/core.py
inventory_foundation_sdk/custom_datasets.py
inventory_foundation_sdk/db_mgmt.py
inventory_foundation_sdk/db_retrievers.py
inventory_foundation_sdk/etl_db_writers.py
inventory_foundation_sdk/etl_nodes.py
inventory_foundation_sdk/kedro_orchestration.py
inventory_foundation_sdk/state_mgmnt.py
inventory_foundation_sdk-0.0.15.dist-info/LICENSE
inventory_foundation_sdk-0.0.15.dist-info/METADATA
inventory_foundation_sdk-0.0.15.dist-info/WHEEL
inventory_foundation_sdk-0.0.15.dist-info/entry_points.txt
inventory_foundation_sdk-0.0.15.dist-info/top_level.txt
inventory_foundation_sdk-0.0.15.dist-info/RECORD
