Metadata-Version: 2.2
Name: inventory_foundation-sdk
Version: 0.0.15
Summary: Central repo with all re-usable code related to the inventory foundation model project
Home-page: https://github.com/d3group/inventory_foundation-sdk
Author: Magnus Maichle
Author-email: magnus.maichle@uni-wuerzburg.de
License: Apache Software License 2.0
Keywords: nbdev jupyter notebook python
Classifier: Development Status :: 4 - Beta
Classifier: Intended Audience :: Developers
Classifier: Natural Language :: English
Classifier: Programming Language :: Python :: 3.7
Classifier: Programming Language :: Python :: 3.8
Classifier: Programming Language :: Python :: 3.9
Classifier: Programming Language :: Python :: 3.10
Classifier: Programming Language :: Python :: 3.11
Classifier: Programming Language :: Python :: 3.12
Classifier: License :: OSI Approved :: Apache Software License
Requires-Python: >=3.7
License-File: LICENSE
Requires-Dist: kedro~=0.19.9
Requires-Dist: psycopg2-binary~=2.9.1
Requires-Dist: pandas>=1.5.0
Requires-Dist: numpy>=1.21.0
Requires-Dist: tqdm~=4.67.1
Requires-Dist: black~=24.10.0
Provides-Extra: dev
Requires-Dist: kedro~=0.19.9; extra == "dev"
Requires-Dist: psycopg2-binary~=2.9.1; extra == "dev"
Requires-Dist: pandas>=1.5.0; extra == "dev"
Requires-Dist: numpy>=1.21.0; extra == "dev"
Requires-Dist: tqdm~=4.67.1; extra == "dev"
Requires-Dist: black~=24.10.0; extra == "dev"
Dynamic: author
Dynamic: author-email
Dynamic: classifier
Dynamic: description
Dynamic: description-content-type
Dynamic: home-page
Dynamic: keywords
Dynamic: license
Dynamic: provides-extra
Dynamic: requires-dist
Dynamic: requires-python
Dynamic: summary
